text2insights/__init__.py
text2insights/keywords.py
text2insights/ner.py
text2insights/sentiment.py
text2insights-0.1.2.dist-info/METADATA
text2insights-0.1.2.dist-info/WHEEL
text2insights-0.1.2.dist-info/top_level.txt
text2insights-0.1.2.dist-info/RECORD
