Metadata-Version: 2.4
Name: text2insights
Version: 0.1.2
Summary: Extract sentiment, keywords, and entities from text.
Author: Lereko Qholosha
Classifier: Programming Language :: Python :: 3
Classifier: License :: OSI Approved :: MIT License
Classifier: Operating System :: OS Independent
Requires-Python: >=3.7
Requires-Dist: textblob
Requires-Dist: spacy
Requires-Dist: scikit-learn
Requires-Dist: numpy
Dynamic: author
Dynamic: classifier
Dynamic: description
Dynamic: description-content-type
Dynamic: requires-dist
Dynamic: requires-python
Dynamic: summary
